r_map/AddressedNode.py
r_map/ArrayedNode.py
r_map/BitField.py
r_map/BitFieldRef.py
r_map/Enumeration.py
r_map/Node.py
r_map/Register.py
r_map/RegisterMap.py
r_map/ValidationError.py
r_map/ValueNodeMixins.py
r_map/__init__.py
r_map/arrayed_node_name_parser.py
r_map/elaborate_tree.py
r_map/serialize.py
r_map-0.9.0.dist-info/LICENSE.txt
r_map-0.9.0.dist-info/METADATA
r_map-0.9.0.dist-info/WHEEL
r_map-0.9.0.dist-info/top_level.txt
r_map-0.9.0.dist-info/RECORD
