Metadata-Version: 2.1
Name: r-map
Version: 0.9.0
Summary: A data structure for working with register map information
Home-page: https://github.com/mentaal/r_map
Author: Gregory Kuhn
Author-email: gregorykuhn@gmail.com
License: UNKNOWN
Project-URL: Bug Reports, https://github.com/mentaal/r_map/issues
Project-URL: Source, https://github.com/mentaal/r_map
Keywords: register bitfield registermap
Platform: UNKNOWN
Classifier: Development Status :: 4 - Beta
Classifier: Intended Audience :: Developers
Classifier: Topic :: Software Development :: Build Tools
Classifier: License :: OSI Approved :: MIT License
Classifier: Programming Language :: Python :: 3.6
Requires-Python: >=3.6
License-File: LICENSE.txt
